pyautoexcel/__init__.py
pyautoexcel-0.1.8.dist-info/LICENSE
pyautoexcel-0.1.8.dist-info/WHEEL
pyautoexcel-0.1.8.dist-info/METADATA
pyautoexcel-0.1.8.dist-info/RECORD
